LICENSE
MANIFEST.in
README.md
README.rst
setup.py
tox.ini
shinto_cli/__init__.py
shinto_cli/cli.py
shinto_cli/context.py
shinto_cli.egg-info/PKG-INFO
shinto_cli.egg-info/SOURCES.txt
shinto_cli.egg-info/dependency_links.txt
shinto_cli.egg-info/entry_points.txt
shinto_cli.egg-info/not-zip-safe
shinto_cli.egg-info/requires.txt
shinto_cli.egg-info/top_level.txt
shinto_cli/extras/__init__.py
shinto_cli/extras/filters.py