Metadata-Version: 2.1
Name: shinto-cli
Version: 0.5.0
Summary: Command-line interface to Jinja2 for templating in shell scripts.
Home-page: https://github.com/istrategylabs/shinto-cli
Author: ISL
Author-email: dev@isl.co
License: BSD
Keywords: Jinja2,templating,command-line,CLI
Platform: any
Classifier: Development Status :: 5 - Production/Stable
Classifier: Intended Audience :: Developers
Classifier: Intended Audience :: System Administrators
Classifier: Operating System :: OS Independent
Classifier: Topic :: Software Development
Classifier: Natural Language :: English
Classifier: Programming Language :: Python :: 2
Provides-Extra: yaml
